hatchling_autoextras_hook/__init__.py
hatchling_autoextras_hook/hooks.py
hatchling_autoextras_hook/py.typed
hatchling_autoextras_hook-0.1.3.dist-info/METADATA
hatchling_autoextras_hook-0.1.3.dist-info/WHEEL
hatchling_autoextras_hook-0.1.3.dist-info/entry_points.txt
hatchling_autoextras_hook-0.1.3.dist-info/licenses/LICENSE
hatchling_autoextras_hook-0.1.3.dist-info/RECORD
