Metadata-Version: 2.4
Name: hatchling-autoextras-hook
Version: 0.1.3
Dynamic: Maintainer
Dynamic: Maintainer-email
Summary: Hatchling metadata hook to generate all extras
Project-URL: homepage, https://github.com/durandtibo/hatchling-autoextras-hook
Project-URL: repository, https://github.com/durandtibo/hatchling-autoextras-hook
Author-email: Thibaut Durand <durand.tibo+gh@gmail.com>
License-Expression: BSD-3-Clause
License-File: LICENSE
Keywords: automation,hatchling,hook,metadata,optional-dependencies
Classifier: Development Status :: 4 - Beta
Classifier: Intended Audience :: Developers
Classifier: Intended Audience :: Information Technology
Classifier: Intended Audience :: Science/Research
Classifier: License :: OSI Approved :: BSD License
Classifier: Operating System :: POSIX :: Linux
Classifier: Programming Language :: Python :: 3.10
Classifier: Programming Language :: Python :: 3.11
Classifier: Programming Language :: Python :: 3.12
Classifier: Programming Language :: Python :: 3.13
Classifier: Programming Language :: Python :: 3.14
Classifier: Topic :: Scientific/Engineering
Classifier: Topic :: Software Development :: Libraries
Requires-Python: >=3.10
Requires-Dist: hatchling<2.0,>=1.18
